aka-1.0.2.data/scripts/aka
aka/__init__.py
aka/actions.py
aka/utils.py
aka-1.0.2.dist-info/RECORD
aka-1.0.2.dist-info/METADATA
aka-1.0.2.dist-info/WHEEL
aka-1.0.2.dist-info/metadata.json
aka-1.0.2.dist-info/top_level.txt
aka-1.0.2.dist-info/DESCRIPTION.rst
