Metadata-Version: 2.0
Name: aka
Version: 1.0.2
Summary: Rename/copy files using Python code
Home-page: https://notabug.org/Uglemat/aka
Author: Mattias Ugelvik
Author-email: uglemat@gmail.com
License: GPL3+
Platform: UNKNOWN
Classifier: Environment :: Console
Classifier: Intended Audience :: System Administrators
Classifier: Intended Audience :: Developers
Classifier: Intended Audience :: End Users/Desktop
Classifier: Topic :: System :: Systems Administration
Classifier: Topic :: Utilities
Classifier: License :: OSI Approved :: GNU General Public License v3 or later (GPLv3+)
Classifier: Programming Language :: Python :: 3
Requires-Dist: contex
